[
  { "id": "KR", "name_kr": "대한민국", "name_en": "South Korea", "lat": 36.5, "lng": 127.5 },
  { "id": "JP", "name_kr": "일본", "name_en": "Japan", "lat": 36.2, "lng": 138.3 },
  { "id": "CN", "name_kr": "중국", "name_en": "China", "lat": 35.9, "lng": 104.2 },
  { "id": "US", "name_kr": "미국", "name_en": "United States", "lat": 39.5, "lng": -98.4 },
  { "id": "GB", "name_kr": "영국", "name_en": "United Kingdom", "lat": 54.0, "lng": -2.0 },
  { "id": "FR", "name_kr": "프랑스", "name_en": "France", "lat": 46.2, "lng": 2.2 },
  { "id": "DE", "name_kr": "독일", "name_en": "Germany", "lat": 51.2, "lng": 10.5 },
  { "id": "IT", "name_kr": "이탈리아", "name_en": "Italy", "lat": 42.8, "lng": 12.8 },
  { "id": "ES", "name_kr": "스페인", "name_en": "Spain", "lat": 40.5, "lng": -3.7 },
  { "id": "PT", "name_kr": "포르투갈", "name_en": "Portugal", "lat": 39.4, "lng": -8.2 },
  { "id": "NL", "name_kr": "네덜란드", "name_en": "Netherlands", "lat": 52.1, "lng": 5.3 },
  { "id": "BE", "name_kr": "벨기에", "name_en": "Belgium", "lat": 50.5, "lng": 4.5 },
  { "id": "SE", "name_kr": "스웨덴", "name_en": "Sweden", "lat": 60.1, "lng": 18.6 },
  { "id": "NO", "name_kr": "노르웨이", "name_en": "Norway", "lat": 64.6, "lng": 17.1 },
  { "id": "DK", "name_kr": "덴마크", "name_en": "Denmark", "lat": 56.3, "lng": 9.5 },
  { "id": "FI", "name_kr": "핀란드", "name_en": "Finland", "lat": 61.9, "lng": 25.7 },
  { "id": "CH", "name_kr": "스위스", "name_en": "Switzerland", "lat": 47.0, "lng": 8.2 },
  { "id": "AT", "name_kr": "오스트리아", "name_en": "Austria", "lat": 47.5, "lng": 14.6 },
  { "id": "PL", "name_kr": "폴란드", "name_en": "Poland", "lat": 51.9, "lng": 19.1 },
  { "id": "RO", "name_kr": "루마니아", "name_en": "Romania", "lat": 45.9, "lng": 24.9 },
  { "id": "GR", "name_kr": "그리스", "name_en": "Greece", "lat": 39.1, "lng": 21.8 },
  { "id": "CZ", "name_kr": "체코", "name_en": "Czech Republic", "lat": 49.8, "lng": 15.5 },
  { "id": "HU", "name_kr": "헝가리", "name_en": "Hungary", "lat": 47.2, "lng": 19.5 },
  { "id": "UA", "name_kr": "우크라이나", "name_en": "Ukraine", "lat": 48.4, "lng": 31.2 },
  { "id": "RU", "name_kr": "러시아", "name_en": "Russia", "lat": 61.5, "lng": 105.3 },
  { "id": "TR", "name_kr": "튀르키예", "name_en": "Turkey", "lat": 38.96, "lng": 35.2 },
  { "id": "SA", "name_kr": "사우디아라비아", "name_en": "Saudi Arabia", "lat": 23.9, "lng": 45.1 },
  { "id": "IR", "name_kr": "이란", "name_en": "Iran", "lat": 32.4, "lng": 53.7 },
  { "id": "IQ", "name_kr": "이라크", "name_en": "Iraq", "lat": 33.2, "lng": 43.7 },
  { "id": "IL", "name_kr": "이스라엘", "name_en": "Israel", "lat": 31.5, "lng": 35.0 },
  { "id": "AE", "name_kr": "아랍에미리트", "name_en": "UAE", "lat": 24.0, "lng": 54.0 },
  { "id": "IN", "name_kr": "인도", "name_en": "India", "lat": 20.6, "lng": 78.9 },
  { "id": "PK", "name_kr": "파키스탄", "name_en": "Pakistan", "lat": 30.4, "lng": 69.3 },
  { "id": "BD", "name_kr": "방글라데시", "name_en": "Bangladesh", "lat": 23.7, "lng": 90.4 },
  { "id": "NP", "name_kr": "네팔", "name_en": "Nepal", "lat": 28.4, "lng": 84.1 },
  { "id": "LK", "name_kr": "스리랑카", "name_en": "Sri Lanka", "lat": 7.9, "lng": 80.8 },
  { "id": "MM", "name_kr": "미얀마", "name_en": "Myanmar", "lat": 17.1, "lng": 96.7 },
  { "id": "TH", "name_kr": "태국", "name_en": "Thailand", "lat": 15.9, "lng": 100.9 },
  { "id": "VN", "name_kr": "베트남", "name_en": "Vietnam", "lat": 14.1, "lng": 108.3 },
  { "id": "PH", "name_kr": "필리핀", "name_en": "Philippines", "lat": 12.9, "lng": 121.8 },
  { "id": "ID", "name_kr": "인도네시아", "name_en": "Indonesia", "lat": -0.8, "lng": 113.9 },
  { "id": "MY", "name_kr": "말레이시아", "name_en": "Malaysia", "lat": 4.2, "lng": 101.9 },
  { "id": "SG", "name_kr": "싱가포르", "name_en": "Singapore", "lat": 1.35, "lng": 103.8 },
  { "id": "KH", "name_kr": "캄보디아", "name_en": "Cambodia", "lat": 12.6, "lng": 104.9 },
  { "id": "MN", "name_kr": "몽골", "name_en": "Mongolia", "lat": 46.9, "lng": 103.8 },
  { "id": "KZ", "name_kr": "카자흐스탄", "name_en": "Kazakhstan", "lat": 48.0, "lng": 66.9 },
  { "id": "AU", "name_kr": "호주", "name_en": "Australia", "lat": -25.3, "lng": 133.8 },
  { "id": "NZ", "name_kr": "뉴질랜드", "name_en": "New Zealand", "lat": -40.9, "lng": 174.9 },
  { "id": "CA", "name_kr": "캐나다", "name_en": "Canada", "lat": 56.1, "lng": -106.3 },
  { "id": "MX", "name_kr": "멕시코", "name_en": "Mexico", "lat": 23.6, "lng": -102.6 },
  { "id": "BR", "name_kr": "브라질", "name_en": "Brazil", "lat": -14.2, "lng": -51.9 },
  { "id": "AR", "name_kr": "아르헨티나", "name_en": "Argentina", "lat": -38.4, "lng": -63.6 },
  { "id": "CL", "name_kr": "칠레", "name_en": "Chile", "lat": -35.7, "lng": -71.5 },
  { "id": "CO", "name_kr": "콜롬비아", "name_en": "Colombia", "lat": 4.6, "lng": -74.3 },
  { "id": "PE", "name_kr": "페루", "name_en": "Peru", "lat": -9.2, "lng": -75.0 },
  { "id": "VE", "name_kr": "베네수엘라", "name_en": "Venezuela", "lat": 6.4, "lng": -66.6 },
  { "id": "EC", "name_kr": "에콰도르", "name_en": "Ecuador", "lat": -1.8, "lng": -78.2 },
  { "id": "BO", "name_kr": "볼리비아", "name_en": "Bolivia", "lat": -16.3, "lng": -63.6 },
  { "id": "UY", "name_kr": "우루과이", "name_en": "Uruguay", "lat": -32.5, "lng": -55.8 },
  { "id": "EG", "name_kr": "이집트", "name_en": "Egypt", "lat": 26.8, "lng": 30.8 },
  { "id": "ZA", "name_kr": "남아프리카 공화국", "name_en": "South Africa", "lat": -30.6, "lng": 22.9 },
  { "id": "NG", "name_kr": "나이지리아", "name_en": "Nigeria", "lat": 9.1, "lng": 8.7 },
  { "id": "KE", "name_kr": "케냐", "name_en": "Kenya", "lat": 0.0, "lng": 37.9 },
  { "id": "ET", "name_kr": "에티오피아", "name_en": "Ethiopia", "lat": 9.1, "lng": 40.5 },
  { "id": "GH", "name_kr": "가나", "name_en": "Ghana", "lat": 7.9, "lng": -1.0 },
  { "id": "MA", "name_kr": "모로코", "name_en": "Morocco", "lat": 31.8, "lng": -7.1 },
  { "id": "DZ", "name_kr": "알제리", "name_en": "Algeria", "lat": 28.0, "lng": 2.6 },
  { "id": "TZ", "name_kr": "탄자니아", "name_en": "Tanzania", "lat": -6.4, "lng": 34.9 },
  { "id": "SD", "name_kr": "수단", "name_en": "Sudan", "lat": 12.9, "lng": 30.2 },
  { "id": "IS", "name_kr": "아이슬란드", "name_en": "Iceland", "lat": 65.0, "lng": -18.0 },
  { "id": "IE", "name_kr": "아일랜드", "name_en": "Ireland", "lat": 53.4, "lng": -8.2 },
  { "id": "HR", "name_kr": "크로아티아", "name_en": "Croatia", "lat": 45.1, "lng": 15.2 },
  { "id": "RS", "name_kr": "세르비아", "name_en": "Serbia", "lat": 44.0, "lng": 21.0 },
  { "id": "BG", "name_kr": "불가리아", "name_en": "Bulgaria", "lat": 42.7, "lng": 25.5 },
  { "id": "SK", "name_kr": "슬로바키아", "name_en": "Slovakia", "lat": 48.7, "lng": 19.7 },
  { "id": "BY", "name_kr": "벨라루스", "name_en": "Belarus", "lat": 53.7, "lng": 27.9 },
  { "id": "UZ", "name_kr": "우즈베키스탄", "name_en": "Uzbekistan", "lat": 41.4, "lng": 64.6 },
  { "id": "MG", "name_kr": "마다가스카르", "name_en": "Madagascar", "lat": -18.8, "lng": 46.9 },
  { "id": "CU", "name_kr": "쿠바", "name_en": "Cuba", "lat": 21.5, "lng": -79.5 },
  { "id": "AF", "name_kr": "아프가니스탄", "name_en": "Afghanistan", "lat": 33.9, "lng": 67.7 },
  { "id": "TW", "name_kr": "대만", "name_en": "Taiwan", "lat": 23.7, "lng": 121.0 }
]
